Babaji/__init__.py
Babaji/demo.py
Babaji/predictor.py
Babaji-2.0.2.dist-info/METADATA
Babaji-2.0.2.dist-info/WHEEL
Babaji-2.0.2.dist-info/top_level.txt
Babaji-2.0.2.dist-info/RECORD
