Metadata-Version: 2.1
Name: Babaji
Version: 2.0.2
Summary: A package in which various of Pretrain models are implemented.
Home-page: https://github.com/PyBabaji
Author: Nachiket Shinde
Author-email: nachiketshinde@gmail.com
Classifier: Programming Language :: Python :: 3
Classifier: License :: OSI Approved :: MIT License
Classifier: Operating System :: OS Independent
Requires-Python: >=3.6
Requires-Dist: scikit-learn
